devicev1/__init__.py
devicev1/device_test.py
devicev1/client/__init__.py
devicev1/client/device_api.py
devicev1/client/device_client.py
devicev1-1.0.0.16.dev3.dist-info/METADATA
devicev1-1.0.0.16.dev3.dist-info/WHEEL
devicev1-1.0.0.16.dev3.dist-info/top_level.txt
devicev1-1.0.0.16.dev3.dist-info/RECORD
