Metadata-Version: 2.1
Name: devicev1
Version: 1.0.0.16.dev3
Summary: Windmill-Device Api Client
Requires-Python: >=3.8
Requires-Dist: bce-python-sdk ==0.8.87
Requires-Dist: pydantic >=2.10
Requires-Dist: bce-internal-sdk
Requires-Dist: typing
Requires-Dist: setuptools
